calysto_chatbot/__init__.py
calysto_chatbot/__main__.py
calysto_chatbot/kernel.py
calysto_chatbot-0.9.1.dist-info/METADATA
calysto_chatbot-0.9.1.dist-info/RECORD
calysto_chatbot-0.9.1.dist-info/WHEEL
calysto_chatbot-0.9.1.dist-info/top_level.txt
